qoala/__init__.py
qoala/arch/components.drawio
qoala/arch/program_classes.drawio
qoala/arch/protocols.drawio
qoala/arch/qoala-runtime-data.drawio
qoala/arch/qoala2.drawio
qoala/arch/runtime_classes.drawio
qoala/lang/__init__.py
qoala/lang/common.py
qoala/lang/ehi.py
qoala/lang/hostlang.py
qoala/lang/parse.py
qoala/lang/program.py
qoala/lang/request.py
qoala/lang/routine.py
qoala/runtime/__init__.py
qoala/runtime/config.py
qoala/runtime/instructions.py
qoala/runtime/lhi.py
qoala/runtime/lhi_to_ehi.py
qoala/runtime/memory.py
qoala/runtime/message.py
qoala/runtime/ntf.py
qoala/runtime/program.py
qoala/runtime/sharedmem.py
qoala/runtime/statistics.py
qoala/runtime/task.py
qoala/sim/__init__.py
qoala/sim/build.py
qoala/sim/componentprot.py
qoala/sim/driver.py
qoala/sim/eprsocket.py
qoala/sim/events.py
qoala/sim/globals.py
qoala/sim/memmgr.py
qoala/sim/network.py
qoala/sim/process.py
qoala/sim/procnode.py
qoala/sim/procnodecomp.py
qoala/sim/qdevice.py
qoala/sim/scheduler.py
qoala/sim/entdist/entdist.py
qoala/sim/entdist/entdistcomp.py
qoala/sim/entdist/entdistinterface.py
qoala/sim/host/__init__.py
qoala/sim/host/csocket.py
qoala/sim/host/host.py
qoala/sim/host/hostcomp.py
qoala/sim/host/hostinterface.py
qoala/sim/host/hostprocessor.py
qoala/sim/netstack/__init__.py
qoala/sim/netstack/netstack.py
qoala/sim/netstack/netstackcomp.py
qoala/sim/netstack/netstackinterface.py
qoala/sim/netstack/netstackprocessor.py
qoala/sim/qnos/__init__.py
qoala/sim/qnos/qnos.py
qoala/sim/qnos/qnoscomp.py
qoala/sim/qnos/qnosinterface.py
qoala/sim/qnos/qnosprocessor.py
qoala/util/__init__.py
qoala/util/builder.py
qoala/util/logging.py
qoala/util/math.py
qoala/util/runner.py
qoala/util/taskgraph.py
qoala/util/tests.py
qoala-1.0.0.dist-info/LICENSE
qoala-1.0.0.dist-info/METADATA
qoala-1.0.0.dist-info/WHEEL
qoala-1.0.0.dist-info/top_level.txt
qoala-1.0.0.dist-info/RECORD
