Metadata-Version: 2.1
Name: qoala
Version: 1.0.0
Summary: Simulator for Qoala programs
Home-page: https://github.com/QuTech-Delft/qoala-sim
Author: QuTech
Author-email: b.vandervecht@tudelft.nl
License: MIT
License-File: LICENSE
Requires-Dist: numpy<1.23,>=1.22
Requires-Dist: pydantic>=1.8.2
Requires-Dist: pydynaa<2.0,>=0.3
Requires-Dist: scipy<2.0.0,>=1.4.1
Requires-Dist: netsquid<2.0,>=1.0.6
Requires-Dist: netsquid-magic<15.0.0,>=14.0
Requires-Dist: netqasm==0.13.0a7
Requires-Dist: networkx==3.1
Requires-Dist: matplotlib==3.6.3
Provides-Extra: dev
Requires-Dist: pytest<8.0,>=7.1; extra == "dev"
Requires-Dist: pytest-xdist<4.0,>=3.1; extra == "dev"
Requires-Dist: coverage>=7.1; extra == "dev"
Requires-Dist: types-PyYAML<7.0,>=6.0; extra == "dev"
Requires-Dist: flake8<5.0,>=4.0; extra == "dev"
Requires-Dist: isort<5.11,>=5.10; extra == "dev"
Requires-Dist: black<22.4,>=22.3; extra == "dev"
Requires-Dist: mypy<1.12,>=1.11.2; extra == "dev"
Requires-Dist: dacite>=1.8.1; extra == "dev"
